[
    {
        "30": "20",
        "TV-1SR ": "TV-5/8SR  "
    },
    {
        "30": "10",
        "TV-1SR ": "TV-1MB "
    },
    {
        "30": "10",
        "TV-1SR ": "TV-5/8MB "
    },
    {
        "30": "8",
        "TV-1SR ": "TV-1DL-BY2"
    },
    {
        "30": "8",
        "TV-1SR ": "TV-5/8DL "
    },
    {
        "30": "12",
        "TV-1SR ": "TV-1HL-BY2"
    },
    {
        "30": "12",
        "TV-1SR ": "TV-5/8HM-BY2"
    },
    {
        "30": "12",
        "TV-1SR ": "TV-5/8HS-BY2"
    },
    {
        "30": "15",
        "TV-1SR ": "TV-REFTV RND LEAS"
    },
    {
        "30": "25",
        "TV-1SR ": "TV-REFTV COLR 12 "
    },
    {
        "30": "5",
        "TV-1SR ": "TV-METAL DOG LEASH-BY1"
    },
    {
        "30": "15",
        "TV-1SR ": "TV-BRAID LEASH 4 "
    },
    {
        "30": "15",
        "TV-1SR ": "TV-BRAID LEASH 5 "
    },
    {
        "30": "5",
        "TV-1SR ": "TV-BRAID LEASH 12-BY2"
    },
    {
        "30": "5",
        "TV-1SR ": "TV-BRAID LEASH 15-BY2"
    },
    {
        "30": "8",
        "TV-1SR ": "TV-3/8\" FLAT LEASH "
    },
    {
        "30": "8",
        "TV-1SR ": "TV-3/8\" COLLAR "
    },
    {
        "30": "25",
        "TV-1SR ": "TV-PRNT HAR&LEAD12 "
    },
    {
        "30": "20",
        "TV-1SR ": "TV-PRINT COL&LEAD12 "
    },
    {
        "30": "10",
        "TV-1SR ": "TV-PRINT COL&LEAD15-BY2"
    },
    {
        "30": "15",
        "TV-1SR ": "TV-REFTV COLR 20 "
    },
    {
        "30": "15",
        "TV-1SR ": "TV-REFTV COLR 25 "
    },
    {
        "30": "30",
        "TV-1SR ": "TV-RND NYL 48\"-8M "
    },
    {
        "30": "10",
        "TV-1SR ": "TV-PEST CONTROL 56-BY2"
    },
    {
        "30": "15",
        "TV-1SR ": "TV-FLEA & TICK-DOGS-BY2"
    },
    {
        "30": "15",
        "TV-1SR ": "TV-FLEA & TICK-XS-BY2"
    },
    {
        "30": "15",
        "TV-1SR ": "TV-PLAIN COLAR&LEAD10"
    },
    {
        "30": "10",
        "TV-1SR ": "TV-3/4 MB "
    },
    {
        "30": "25",
        "TV-1SR ": "TV-3/8 PRNTD COLLAR"
    },
    {
        "30": "8",
        "TV-1SR ": "TV-PRNTED COLAR 25M-BY2"
    },
    {
        "30": "20",
        "TV-1SR ": "TV-PLSTC D BOWL-4\"-BY2"
    },
    {
        "30": "20",
        "TV-1SR ": "TV-PLAIN D BOWL-SML-BY2"
    },
    {
        "30": "15",
        "TV-1SR ": "TV-PLAIN D BOWL-07-MED-BY2"
    },
    {
        "30": "8",
        "TV-1SR ": "TV-PRNTD DBOWL-SML-BY2"
    },
    {
        "30": "12",
        "TV-1SR ": "TV-PRNTD DBOWL-05-MED-BY2"
    },
    {
        "30": "10",
        "TV-1SR ": "TV-PRNTD DBOWL-LRG-BY2"
    },
    {
        "30": "20",
        "TV-1SR ": "TV-A-08 DBOWL OVAL-BY2"
    },
    {
        "30": "20",
        "TV-1SR ": "TV-DBOWL OVAL-SML-BY2"
    },
    {
        "30": "10",
        "TV-1SR ": "TV-DGBOWL BAMBOO#1-BY2"
    },
    {
        "30": "20",
        "TV-1SR ": "TV-RND STNLES DB-32-BY2"
    },
    {
        "30": "20",
        "TV-1SR ": "TV-RND STNLES DB-64-BY2"
    },
    {
        "30": "5",
        "TV-1SR ": "TV-NO TIP STAINLES-16.5-BY1"
    },
    {
        "30": "10",
        "TV-1SR ": "TV-RND STAINLESS DB-20-BY2"
    },
    {
        "30": "15",
        "TV-1SR ": "TV-DOG CHEW BONE"
    },
    {
        "30": "15",
        "TV-1SR ": "TV-CHEW BONE 4.5-2pc"
    },
    {
        "30": "15",
        "TV-1SR ": "TV-PRESS BONE 6.5\""
    },
    {
        "30": "15",
        "TV-1SR ": "TV-MINI SAUSAGE "
    },
    {
        "30": "15",
        "TV-1SR ": "TV-MINI CHEW BONE #4"
    },
    {
        "30": "15",
        "TV-1SR ": "TV-CHEW STICKS"
    },
    {
        "30": "40",
        "TV-1SR ": "TV-TRAINTREAT BEFCHES-1"
    },
    {
        "30": "40",
        "TV-1SR ": "TV-TRAINTREAT BEFCHES-2"
    },
    {
        "30": "40",
        "TV-1SR ": "TV-TRAINTREAT BEFCHES-3"
    },
    {
        "30": "40",
        "TV-1SR ": "TV-TRAINTREAT BEEF4"
    },
    {
        "30": "40",
        "TV-1SR ": "TV-TRAINTREAT BEFSPIRLIN5"
    },
    {
        "30": "40",
        "TV-1SR ": "TV-TRAINTREAT BEFBLBERY6"
    },
    {
        "30": "20",
        "TV-1SR ": "TV-STEEL COMB"
    },
    {
        "30": "20",
        "TV-1SR ": "TV-STEELCOMB-RUB.HDL"
    },
    {
        "30": "15",
        "TV-1SR ": "TV-2X SIDE BRUSH-BY2"
    },
    {
        "30": "30",
        "TV-1SR ": "TV-BRUSH OVAL PLSTC"
    },
    {
        "30": "10",
        "TV-1SR ": "TV-BRUSH W HDLE#8-BY1"
    },
    {
        "30": "10",
        "TV-1SR ": "TV-DCHAIN LEAS-3.5 "
    },
    {
        "30": "10",
        "TV-1SR ": "TV-DCHAIN LEAS-4.0 "
    },
    {
        "30": "5",
        "TV-1SR ": "TV-CHAIN EXTNSION 4.0 "
    },
    {
        "30": "30",
        "TV-1SR ": "TV-CC BALL - MED"
    },
    {
        "30": "30",
        "TV-1SR ": "TV-CC BALL - LRG"
    },
    {
        "30": "30",
        "TV-1SR ": "TV-RUB TOY ASRTD#1"
    },
    {
        "30": "30",
        "TV-1SR ": "TV-DOG TOY ROPE #1"
    },
    {
        "30": "30",
        "TV-1SR ": "TV-PET FOODBALL"
    },
    {
        "30": "25",
        "TV-1SR ": "TV-SCENTED BONE"
    },
    {
        "30": "30",
        "TV-1SR ": "TV-RUBBER BONE #2"
    },
    {
        "30": "30",
        "TV-1SR ": "TV-RUBBER BONE #3"
    },
    {
        "30": "30",
        "TV-1SR ": "TV-RUBBER BONE #4"
    },
    {
        "30": "15",
        "TV-1SR ": "TV-WATER FEEDER -BY2"
    },
    {
        "30": "5",
        "TV-1SR ": "TV-MUZZLE-A40-#4420-BY2"
    },
    {
        "30": "5",
        "TV-1SR ": "TV-MUZZLE-A411-#4423-BY2"
    },
    {
        "30": "5",
        "TV-1SR ": "TV-MUZZLE-A412-#4421-BY2"
    },
    {
        "30": "10",
        "TV-1SR ": "TV-MUZZLE-A413-#4424-BY2"
    },
    {
        "30": "10",
        "TV-1SR ": "TV-N TRIM #02-BY2"
    },
    {
        "30": "10",
        "TV-1SR ": "TV-N TRIM WT NAIL FILE-BY2"
    }
]